[1,["ecpdLyjvZBwrvm+cedCcQy","65T7v2XzxLAYvVQV057Fuk","bcZhHs9nNO47ph6dfDbkLz","21JQ9KSoRJ56/8B6fAgz6w","efwgN0gx1Kl6h6bHRw5rUE","75a6jqwwFEyYHos3LK+enp","61ZiKwwhpHCoBTp4Lzrb4B","31Rc3Jv4hNMat/RW8efOT3","57gk/FCPJEtLJitmzHC0Xz","3c4q2ulORDdIH/KRYxZvV3","10b8gbUMRJvKR9UlXwIfqs","ferBUwRqlJWIaD4FWGpy2l","2cJ8rl5dJHZbibRiqO46oM","e8yI9IzjpOT520Oe8m2g/e","3fiL6Jbl5LF5svXvSHVDhC","3fZsjeihhGK5fageBtwj3X","5f5dyqtRNNxaFmVzYns6FZ","9bvaMerUlDyary99mJa6xp","5cO7kybDxGj4ipyMYdRYZB","233AS/SrtOLq3HL8FLhbTU","abDTVBCFVLhIIHMhRwwJTI","05BngZYcFOr4YztZ8NAsfJ","eaBKI+cgxBn4SKrQ8r+HgM","3c32HSsAVES6EIyblOfYsw","eezbuN0hlMK4USQLcSquGW","6bHSK24xtAWrC8i6BtCEzi","aaWVGWnM1G3LWgVYVw768P"],["node","_spriteFrame","_N$file","_textureSetter","btn_visit","label_unlock","lock","root","btn_close","data","_parent","_scrollView"],["cc.SpriteFrame",["cc.Node",["_name","_active","_components","_prefab","_contentSize","_parent","_children","_trs","_anchorPoint","_color"],1,9,4,5,1,2,7,5,5],["cc.Sprite",["_sizeMode","_type","_enabled","node","_materials","_spriteFrame"],0,1,3,6],["cc.Widget",["_alignFlags","_originalHeight","_right","_top","alignMode","_left","_originalWidth","node"],-4,1],["cc.Label",["_string","_isSystemFontUsed","_fontSize","_lineHeight","_N$verticalAlign","_N$horizontalAlign","node","_materials","_N$file"],-3,1,3,6],["cc.Node",["_name","_active","_parent","_children","_components","_prefab","_contentSize","_trs","_anchorPoint"],1,1,2,12,4,5,7,5],["cc.Node",["_name","_parent","_components","_prefab","_contentSize","_trs","_anchorPoint"],2,1,2,4,5,7,5],["cc.PrefabInfo",["fileId","root"],2,1],["b4f8dfH/vNPlbUDa29iHr/4",["kingdomName","levelUnlock","node","lock","label_unlock","btn_visit"],1,1,1,1,1],["cc.Button",["_N$transition","node","clickEvents"],2,1,9],["cc.LabelOutline",["_width","_enabled","node","_color"],1,1,5],["cc.Prefab",["_name"],2],["c2275xqQlJDeJ0UQZf4qoVl",["node","btn_close"],3,1,1],["cc.Layout",["_resize","_N$layoutType","_N$paddingLeft","_N$paddingTop","_N$spacingX","_N$spacingY","node","_layoutSize"],-3,1,5],["329b7HJOYxDNpEiugde1Lb0",["key","node"],2,1],["cc.Mask",["_N$alphaThreshold","node","_materials"],2,1,3],["cc.Scrollbar",["_N$direction","node","_N$handle"],2,1,1],["cc.ScrollView",["horizontal","brake","bounceDuration","_N$horizontalScrollBar","node","_N$content","_N$verticalScrollBar"],-1,1,1,1],["cc.ClickEvent",["_componentId","handler","target"],1,1]],[[7,0,1,2],[1,0,5,2,3,4,7,2],[2,3,4,5,1],[14,0,1,2],[2,0,3,4,5,2],[4,0,2,3,1,5,4,6,7,8,7],[1,0,5,6,2,3,4,7,2],[1,0,5,2,3,9,4,7,2],[1,0,5,2,3,4,2],[6,0,1,2,3,4,5,2],[9,0,1,2,2],[10,0,2,3,2],[18,0,1,2,3],[5,0,1,2,3,4,5,6,7,3],[8,0,1,2,3,4,5,3],[4,0,2,3,1,5,4,6,7,7],[5,0,2,3,4,5,6,7,2],[2,1,0,3,4,5,3],[11,0,2],[1,0,6,2,3,2],[1,0,6,2,3,4,8,7,2],[1,0,5,6,2,3,4,2],[1,0,1,5,6,2,3,4,7,3],[5,0,1,2,3,4,5,6,8,7,3],[6,0,1,2,3,4,6,5,2],[12,0,1,1],[7,1,1],[3,0,7,2],[3,0,2,3,7,4],[3,4,0,5,1,7,5],[3,0,6,1,7,4],[13,0,1,2,3,4,5,6,7,7],[8,0,2,3,4,5,2],[2,2,1,0,3,4,5,4],[2,1,0,3,4,3],[9,0,1,2],[4,0,1,6,7,8,3],[4,0,2,3,1,4,6,7,6],[10,1,0,2,3,3],[15,0,1,2,2],[16,0,1,2,2],[17,0,1,2,3,4,5,6,5]],[[[{"name":"earth","rect":[0,0,222,214],"offset":[0,0],"originalSize":[222,214],"capInsets":[0,0,0,0]}],[0],0,[0],[3],[6]],[[{"name":"land-title-bg","rect":[0,0,242,45],"offset":[0,0],"originalSize":[242,45],"capInsets":[0,0,0,0]}],[0],0,[0],[3],[7]],[[[18,"SelectKingdomPopup"],[19,"SelectKingdomPopup",[-4,-5,-6,-7],[[25,-3,-2]],[26,-1]],[20,"content",[-10,-11,-12,-13,-14,-15],[[27,1,-8],[31,1,3,20,5,20,10,-9,[5,580,1075]]],[0,"86jdzBPl5JB4x4D957m5Us",1],[5,580,1075],[0,0.5,1],[0,544,0,0,0,0,1,1,1,1]],[6,"earth",2,[-20,-21,-22,-23,-24,-25],[[32,"earth",-19,-18,-17,-16]],[0,"9f1SYiBdpMD44N4dXRCbgg",1],[5,262,350],[-139,-180,0,0,0,0,1,1,1,0]],[6,"iceland",2,[-30,-31,-32,-33,-34,-35],[[14,"iceland",200,-29,-28,-27,-26]],[0,"b1twWb44lG94Oj0Q250Yjt",1],[5,262,350],[143,-180,0,0,0,0,1,1,1,0]],[6,"autumn",2,[-40,-41,-42,-43,-44,-45],[[14,"autumn",-1,-39,-38,-37,-36]],[0,"02XMnq/vdCDJYfIF09MXla",1],[5,262,350],[-139,-540,0,0,0,0,1,1,1,0]],[6,"winter",2,[-50,-51,-52,-53,-54,-55],[[14,"winter",-1,-49,-48,-47,-46]],[0,"a2spNx+FpGHLmGWsIlYtNX",1],[5,262,350],[143,-540,0,0,0,0,1,1,1,0]],[6,"park",2,[-60,-61,-62,-63,-64,-65],[[14,"park",-1,-59,-58,-57,-56]],[0,"36hV4LOmtBDo82KJtX5bei",1],[5,262,350],[-139,-900,0,0,0,0,1,1,1,0]],[6,"future",2,[-70,-71,-72,-73,-74,-75],[[14,"future",-1,-69,-68,-67,-66]],[0,"8979A/SqZFP4q+ILAsT8rq",1],[5,262,350],[143,-900,0,0,0,0,1,1,1,0]],[1,"btn_close",1,[[2,-76,[2],3],[35,3,-77],[28,33,-278.028,-629.39,-78]],[0,"8fcwwYPlNApKcr/5/JB0Iw",1],[5,76,73],[240.02800000000002,592.89,0,0,0,0,1,1,1,0]],[16,"ListKingdom",1,[-81,-82],[[[33,false,1,0,-79,[100],101],-80],4,1],[0,"04NaY9p1hEeLpsHkQVSwDo",1],[5,580,1088],[-1,-19,0,0,0,0,1,1,1,1]],[23,"scrollBar",false,10,[-86],[[-83,[29,0,37,350.07654921020657,237,-84],[17,1,0,-85,[98],99]],1,4,4],[0,"33wFXAXwVIOKxr9Br7+4E/",1],[5,12,935],[0,1,0.5],[260,0,0,0,0,0,1,1,1,1]],[1,"title",1,[[36,"KINGDOM",false,-87,[4],5],[38,false,3,-88,[4,4278190080]],[3,"kingdom",-89]],[0,"b4BcVBf41MKLqBd9xjmZG0",1],[5,144.3,50.4],[0,561.148,0,0,0,0,1,1,1,1]],[21,"view",10,[2],[[39,0,-90,[7]],[30,45,240,250,-91]],[0,"78dFrJ3zZN6L3BYUUhJmzX",1],[5,580,1088]],[16,"btn_visit",3,[-94],[[[2,-92,[18],19],-93],4,1],[0,"7ewa82sghOn5eSAxVb7Jx8",1],[5,191,57],[0,-136.332,0,0,0,0,1,1,1,0]],[1,"label",14,[[5,"VISIT",32,32,false,1,1,-95,[16],17],[11,3,-96,[4,4278190080]],[3,"visit",-97]],[0,"ddyVHvtFJGJrmMb3RkxYzm",1],[5,66.16,46.32],[0,1.593,0,0,0,0,1,1,1,1]],[22,"lock",false,3,[-99],[[4,0,-98,[21],22]],[0,"7bgcsZ821LV5pkRucrLgxv",1],[5,180,40.8],[0,-142.998,0,0,0,0,1,1,1,1]],[13,"btn_visit",false,4,[-102],[[[2,-100,[33],34],-101],4,1],[0,"34127a0ZRNWJv8UD7EqqSP",1],[5,191,57],[0,-136.332,0,0,0,0,1,1,1,1]],[1,"label",17,[[5,"VISIT",32,32,false,1,1,-103,[31],32],[3,"visit",-104],[11,3,-105,[4,4278190080]]],[0,"f9shea+ypDMbj04mtJnpT1",1],[5,87.66,46.32],[0,1.593,0,0,0,0,1,1,1,1]],[6,"lock",4,[-107],[[4,0,-106,[36],37]],[0,"059+gvYy9DK7OdT37VhYXx",1],[5,180,40.8],[0,-142.998,0,0,0,0,1,1,1,1]],[13,"btn_visit",false,5,[-110],[[[2,-108,[48],49],-109],4,1],[0,"c45JiID3tAmY4rj6Dq/5B2",1],[5,191,57],[0,-136.332,0,0,0,0,1,1,1,1]],[1,"label",20,[[5,"VISIT",32,32,false,1,1,-111,[46],47],[3,"visit",-112],[11,3,-113,[4,4278190080]]],[0,"f4rDFjLsVCzZ7rdva9Tw1p",1],[5,87.66,46.32],[0,1.593,0,0,0,0,1,1,1,1]],[6,"lock",5,[-115],[[4,0,-114,[51],52]],[0,"3cvqLE+ehDgZS0daXR6uJk",1],[5,180,40.8],[0,-142.998,0,0,0,0,1,1,1,1]],[13,"btn_visit",false,6,[-118],[[[2,-116,[63],64],-117],4,1],[0,"12SmWgwXlFupLvci/xQZHc",1],[5,191,57],[0,-136.332,0,0,0,0,1,1,1,1]],[1,"label",23,[[5,"VISIT",32,32,false,1,1,-119,[61],62],[3,"visit",-120],[11,3,-121,[4,4278190080]]],[0,"2ch93droBHuYxy+nhecnr1",1],[5,87.66,46.32],[0,1.593,0,0,0,0,1,1,1,1]],[6,"lock",6,[-123],[[4,0,-122,[66],67]],[0,"c6UQXOrBtC5JcJ8SiuqG7l",1],[5,180,40.8],[0,-142.998,0,0,0,0,1,1,1,1]],[13,"btn_visit",false,7,[-126],[[[2,-124,[78],79],-125],4,1],[0,"d18mWFoRVGCL81SF2SPf5D",1],[5,191,57],[0,-136.332,0,0,0,0,1,1,1,1]],[1,"label",26,[[5,"VISIT",32,32,false,1,1,-127,[76],77],[3,"visit",-128],[11,3,-129,[4,4278190080]]],[0,"84oHhUQ+NCYor36hjx0ckJ",1],[5,87.66,46.32],[0,1.593,0,0,0,0,1,1,1,1]],[6,"lock",7,[-131],[[4,0,-130,[81],82]],[0,"cafXI+QNhLsJG33zvOdGBJ",1],[5,180,40.8],[0,-142.998,0,0,0,0,1,1,1,1]],[13,"btn_visit",false,8,[-134],[[[2,-132,[93],94],-133],4,1],[0,"41ejW3ly5HTLgVZYAQG2/S",1],[5,191,57],[0,-136.332,0,0,0,0,1,1,1,1]],[1,"label",29,[[5,"VISIT",32,32,false,1,1,-135,[91],92],[3,"visit",-136],[11,3,-137,[4,4278190080]]],[0,"10INjo3ktMf6oHi2Gdq1SN",1],[5,87.66,46.32],[0,1.593,0,0,0,0,1,1,1,1]],[6,"lock",8,[-139],[[4,0,-138,[96],97]],[0,"76FaPAiLdAmIUwOr9y2gQr",1],[5,180,40.8],[0,-142.998,0,0,0,0,1,1,1,1]],[7,"title",3,[[5,"EARTH",35,36,false,1,1,-140,[12],13],[3,"earth",-141]],[0,"b45ySWSgxBd65hfdJ/jb2v",1],[4,4278725790],[5,84.44,45.36],[0,147.833,0,0,0,0,1,1,1,1]],[7,"title",4,[[5,"ICELAND",35,36,false,1,1,-142,[27],28],[3,"iceland",-143]],[0,"4aZPko4/BDr7dLCmx6HXtL",1],[4,4278725790],[5,110.08,45.36],[0,147.833,0,0,0,0,1,1,1,1]],[7,"title",5,[[5,"DESERT",35,36,false,1,1,-144,[42],43],[3,"desert",-145]],[0,"a1fKXOmrZKhpxZ+LTMD7Mz",1],[4,4278725790],[5,94.73,45.36],[0,147.833,0,0,0,0,1,1,1,1]],[7,"title",6,[[5,"INFERNO",35,36,false,1,1,-146,[57],58],[3,"inferno",-147]],[0,"60YsOUPKlMzYMAIhuhKnw3",1],[4,4278725790],[5,116.86,45.36],[0,147.833,0,0,0,0,1,1,1,1]],[7,"title",7,[[5,"JADE MOUNTAIN",35,36,false,1,1,-148,[72],73],[3,"jade",-149]],[0,"aft7R+eO1GxLRSPwxyWlRA",1],[4,4278725790],[5,211.93,45.36],[0,147.833,0,0,0,0,1,1,1,1]],[7,"title",8,[[5,"OLYMPUS",35,36,false,1,1,-150,[87],88],[3,"olympus",-151]],[0,"31FIG7P6hHtI2Rq7fpz+Zf",1],[4,4278725790],[5,122.96,45.36],[0,147.833,0,0,0,0,1,1,1,1]],[1,"bg",1,[[17,1,0,-152,[0],1]],[0,"e4FwybPl1F6IXOlgeWcDcm",1],[5,657,1240],[13,-1,0,0,0,0,1,1,1,1]],[24,"bar",11,[-153],[0,"942jZAxjJPbb3LpWkq87uM",1],[5,10,30],[0,1,0],[-1,0,0,0,0,0,1,1,1,1]],[34,1,0,39,[6]],[40,1,11,40],[41,false,0.75,0.23,null,10,2,41],[8,"bg_item",3,[[4,0,-154,[8],9]],[0,"02L6lbYjNPsKFcTxfu0jr4",1],[5,262,350]],[1,"bg_title",3,[[2,-155,[10],11]],[0,"2c6KO0YLFAB6zdb2ueqb8Y",1],[5,242,45],[0,147.178,0,0,0,0,1,1,1,1]],[1,"image",3,[[2,-156,[14],15]],[0,"12rWnbjPdOrYs0ZUOoUevB",1],[5,222,214],[0,5.236,0,0,0,0,1,1,1,1]],[10,3,14,[[12,"b4f8dfH/vNPlbUDa29iHr/4","onVisit",3]]],[9,"label_unlock",16,[-157],[0,"75x7b81AlLRpim024o2xJY",1],[5,99.26,31.5],[16.085,-1.855,0,0,0,0,1,1,1,1]],[15,"LEVEL 200",24,25,false,1,1,47,[20]],[8,"bg_item",4,[[4,0,-158,[23],24]],[0,"19u5LKA91LCZnW8OmBj/eV",1],[5,262,350]],[1,"bg_title",4,[[2,-159,[25],26]],[0,"1fTv1aCGZFvovz83BnkYwz",1],[5,242,45],[0,147.178,0,0,0,0,1,1,1,1]],[1,"image",4,[[2,-160,[29],30]],[0,"37hxO6MldBNJn4F8S2o7vp",1],[5,216,218],[0,-10.844,0,0,0,0,1,1,1,1]],[10,3,17,[[12,"b4f8dfH/vNPlbUDa29iHr/4","onVisit",4]]],[9,"label_unlock",19,[-161],[0,"7d4E1AFUhI0J78jbzkjcYD",1],[5,99.26,32.76],[16.085,-1.855,0,0,0,0,1,1,1,1]],[37,"LEVEL 200",24,26,false,1,53,[35]],[8,"bg_item",5,[[4,0,-162,[38],39]],[0,"1cUBjW13ZNgaMLa0An7aII",1],[5,262,350]],[1,"bg_title",5,[[2,-163,[40],41]],[0,"0eTNBIvp9KhaMaHRSOEyPD",1],[5,242,45],[0,147.178,0,0,0,0,1,1,1,1]],[1,"image",5,[[2,-164,[44],45]],[0,"aad8FDp99I6oz7+Tkeq1OC",1],[5,220,198],[0,-10.844,0,0,0,0,1,1,1,1]],[10,3,20,[[12,"b4f8dfH/vNPlbUDa29iHr/4","onVisit",5]]],[9,"label_unlock",22,[-165],[0,"ec/6yYpFdEJLfEq3CQpfon",1],[5,99.26,31.5],[16.085,-1.855,0,0,0,0,1,1,1,1]],[15,"LEVEL 200",24,25,false,1,1,59,[50]],[8,"bg_item",6,[[4,0,-166,[53],54]],[0,"489NP36xlAHJA8jo53JLHt",1],[5,262,350]],[1,"bg_title",6,[[2,-167,[55],56]],[0,"f5fJjUb9VP65pWsNVFe8+x",1],[5,242,45],[0,147.178,0,0,0,0,1,1,1,1]],[1,"image",6,[[2,-168,[59],60]],[0,"22OwYRWbpOE50wYBejSsZS",1],[5,210,198],[0,-10.844,0,0,0,0,1,1,1,1]],[10,3,23,[[12,"b4f8dfH/vNPlbUDa29iHr/4","onVisit",6]]],[9,"label_unlock",25,[-169],[0,"882nQWdIJLJaYVx1IIWep7",1],[5,99.26,31.5],[16.085,-1.855,0,0,0,0,1,1,1,1]],[15,"LEVEL 200",24,25,false,1,1,65,[65]],[8,"bg_item",7,[[4,0,-170,[68],69]],[0,"e4A7xdEXhAXZOLpgEJIQSD",1],[5,262,350]],[1,"bg_title",7,[[2,-171,[70],71]],[0,"6e/v1EF5lLzJjlbmKuxjKv",1],[5,242,45],[0,147.178,0,0,0,0,1,1,1,1]],[1,"image",7,[[2,-172,[74],75]],[0,"6fqgHsnRZA1b1U2aa3w6lP",1],[5,232,209],[0,-10.844,0,0,0,0,1,1,1,1]],[10,3,26,[[12,"b4f8dfH/vNPlbUDa29iHr/4","onVisit",7]]],[9,"label_unlock",28,[-173],[0,"dbZpqxvwpIEJVZei1tAgCJ",1],[5,99.26,31.5],[16.085,-1.855,0,0,0,0,1,1,1,1]],[15,"LEVEL 200",24,25,false,1,1,71,[80]],[8,"bg_item",8,[[4,0,-174,[83],84]],[0,"0eGRMmsbZOyIhoIypwMlu4",1],[5,262,350]],[1,"bg_title",8,[[2,-175,[85],86]],[0,"78axLy0ulM3qWt2BvbLoXl",1],[5,242,45],[0,147.178,0,0,0,0,1,1,1,1]],[1,"image",8,[[2,-176,[89],90]],[0,"29/vmsoh1A7JxmRB3cNXTQ",1],[5,227,215],[0,-10.844,0,0,0,0,1,1,1,1]],[10,3,29,[[12,"b4f8dfH/vNPlbUDa29iHr/4","onVisit",8]]],[9,"label_unlock",31,[-177],[0,"3bwdv/9cxNPqi/iBZUPa4Z",1],[5,99.26,31.5],[16.085,-1.855,0,0,0,0,1,1,1,1]],[15,"LEVEL 200",24,25,false,1,1,77,[95]]],0,[0,7,1,0,8,9,0,0,1,0,-1,38,0,-2,9,0,-3,12,0,-4,10,0,0,2,0,0,2,0,-1,3,0,-2,4,0,-3,5,0,-4,6,0,-5,7,0,-6,8,0,4,46,0,5,48,0,6,16,0,0,3,0,-1,43,0,-2,44,0,-3,32,0,-4,45,0,-5,14,0,-6,16,0,4,52,0,5,54,0,6,19,0,0,4,0,-1,49,0,-2,50,0,-3,33,0,-4,51,0,-5,17,0,-6,19,0,4,58,0,5,60,0,6,22,0,0,5,0,-1,55,0,-2,56,0,-3,34,0,-4,57,0,-5,20,0,-6,22,0,4,64,0,5,66,0,6,25,0,0,6,0,-1,61,0,-2,62,0,-3,35,0,-4,63,0,-5,23,0,-6,25,0,4,70,0,5,72,0,6,28,0,0,7,0,-1,67,0,-2,68,0,-3,36,0,-4,69,0,-5,26,0,-6,28,0,4,76,0,5,78,0,6,31,0,0,8,0,-1,73,0,-2,74,0,-3,37,0,-4,75,0,-5,29,0,-6,31,0,0,9,0,0,9,0,0,9,0,0,10,0,-2,42,0,-1,11,0,-2,13,0,-1,41,0,0,11,0,0,11,0,-1,39,0,0,12,0,0,12,0,0,12,0,0,13,0,0,13,0,0,14,0,-2,46,0,-1,15,0,0,15,0,0,15,0,0,15,0,0,16,0,-1,47,0,0,17,0,-2,52,0,-1,18,0,0,18,0,0,18,0,0,18,0,0,19,0,-1,53,0,0,20,0,-2,58,0,-1,21,0,0,21,0,0,21,0,0,21,0,0,22,0,-1,59,0,0,23,0,-2,64,0,-1,24,0,0,24,0,0,24,0,0,24,0,0,25,0,-1,65,0,0,26,0,-2,70,0,-1,27,0,0,27,0,0,27,0,0,27,0,0,28,0,-1,71,0,0,29,0,-2,76,0,-1,30,0,0,30,0,0,30,0,0,30,0,0,31,0,-1,77,0,0,32,0,0,32,0,0,33,0,0,33,0,0,34,0,0,34,0,0,35,0,0,35,0,0,36,0,0,36,0,0,37,0,0,37,0,0,38,0,-1,40,0,0,43,0,0,44,0,0,45,0,-1,48,0,0,49,0,0,50,0,0,51,0,-1,54,0,0,55,0,0,56,0,0,57,0,-1,60,0,0,61,0,0,62,0,0,63,0,-1,66,0,0,67,0,0,68,0,0,69,0,-1,72,0,0,73,0,0,74,0,0,75,0,-1,78,0,9,1,2,10,13,41,11,42,177],[0,0,0,0,0,0,0,0,0,0,0,0,0,0,0,0,0,0,0,0,0,0,0,0,0,0,0,0,0,0,0,0,0,0,0,0,0,0,0,0,0,0,0,0,0,0,0,0,0,0,0,0,0,0,0,0,0,0,0,0,0,0,0,0,0,0,0,0,0,0,0,0,0,0,0,0,0,0,0,0,0,0,0,0,0,0,0,0,0,0,0,0,0,0,0,0,0,0,0,0,0,0,40,48,54,60,66,72,78],[-1,1,-1,1,-1,2,-1,-1,-1,1,-1,1,-1,2,-1,1,-1,2,-1,1,-1,-1,1,-1,1,-1,1,-1,2,-1,1,-1,2,-1,1,-1,-1,1,-1,1,-1,1,-1,2,-1,1,-1,2,-1,1,-1,-1,1,-1,1,-1,1,-1,2,-1,1,-1,2,-1,1,-1,-1,1,-1,1,-1,1,-1,2,-1,1,-1,2,-1,1,-1,-1,1,-1,1,-1,1,-1,2,-1,1,-1,2,-1,1,-1,-1,1,-1,1,-1,1,1,2,2,2,2,2,2],[0,8,0,9,0,1,0,0,0,2,0,3,0,1,0,10,0,1,0,4,0,0,5,0,2,0,3,0,1,0,11,0,1,0,4,0,0,5,0,2,0,3,0,1,0,12,0,1,0,4,0,0,5,0,2,0,3,0,1,0,13,0,1,0,4,0,0,5,0,2,0,3,0,1,0,14,0,1,0,4,0,0,5,0,2,0,3,0,1,0,15,0,1,0,4,0,0,5,0,16,0,17,18,1,1,1,1,1,1]],[[{"name":"desert","rect":[0,0,220,198],"offset":[0,0],"originalSize":[220,198],"capInsets":[0,0,0,0]}],[0],0,[0],[3],[19]],[[{"name":"olympus","rect":[0,0,227,215],"offset":[0,0],"originalSize":[227,215],"capInsets":[0,0,0,0]}],[0],0,[0],[3],[20]],[[{"name":"jade_mountain","rect":[0,0,232,209],"offset":[0,0],"originalSize":[232,209],"capInsets":[0,0,0,0]}],[0],0,[0],[3],[21]],[[{"name":"lock","rect":[0,0,130,34],"offset":[0,0],"originalSize":[130,34],"capInsets":[36,0,19,0]}],[0],0,[0],[3],[22]],[[{"name":"land-bg","rect":[0,0,262,356],"offset":[0,0],"originalSize":[262,356],"capInsets":[0,0,0,0]}],[0],0,[0],[3],[23]],[[{"name":"inferno","rect":[0,0,210,198],"offset":[0,0],"originalSize":[210,198],"capInsets":[0,0,0,0]}],[0],0,[0],[3],[24]],[[{"name":"visit-btn","rect":[0,0,191,57],"offset":[0,0],"originalSize":[191,57],"capInsets":[0,0,0,0]}],[0],0,[0],[3],[25]],[[{"name":"iceland","rect":[0,0,216,218],"offset":[0,0],"originalSize":[216,218],"capInsets":[0,0,0,0]}],[0],0,[0],[3],[26]]]]