[1,["511N46eJVL/5Diy6fah4WP","f3RY4X7EdPSrxHqfwubdxc","ecpdLyjvZBwrvm+cedCcQy","a2nnNbRPdGo6lwuTslRfP0","087e12z29NWYwdNud8PyAK"],["node","_textureSetter","root","collision","main_rig","model_node","data","_spriteFrame"],["cc.SpriteFrame",["cc.Prefab",["_name"],2],["cc.Node",["_name","_groupIndex","_components","_prefab","_contentSize"],1,12,4,5],["cc.Sprite",["node","_materials","_spriteFrame"],3,1,3,6],["cc.PhysicsCircleCollider",["_density","_restitution","_radius","node"],0,1],["cc.CircleCollider",["_radius","node"],2,1],["1f858xqxGhISKxC1uJbUyRF",["object_type","node","frame_rage","model_node","main_rig","collision","sfx_collection"],2,1,3,1,1,1,4],["AudioInformation",[],3],["cc.PrefabInfo",["root"],3,1],["cc.RigidBody",["_gravityScale","node"],2,1],["972fagnS5RCV7DBQ88ri4Nf",["node"],3,1]],[[1,0,2],[2,0,1,2,3,4,3],[3,0,1,2,1],[4,0,1,2,3,4],[5,0,1,2],[6,0,1,2,3,4,5,6,2],[7,1],[8,0,1],[9,0,1,2],[10,0,1]],[[[{"name":"Rock","rect":[0,0,25,19],"offset":[0,0],"originalSize":[25,19],"capInsets":[0,0,0,0]}],[0],0,[0],[1],[1]],[[[0,"RockGO"],[1,"Rock",9,[[[2,-2,[0],1],-3,[3,20,0.1,6,-4],[4,10,-5],-6,[5,103,-10,[2,3],-9,-8,-7,[6]]],4,1,4,4,1,4],[7,-1],[5,25,19]],[8,3,1],[9,1]],0,[0,2,1,0,0,1,0,-2,2,0,0,1,0,0,1,0,-5,3,0,3,3,0,4,2,0,5,1,0,0,1,0,6,1,10],[0,0,0,0],[-1,7,-1,-2],[2,0,0,3]],[[{"name":"Rock2","rect":[0,0,25,18],"offset":[0,0],"originalSize":[25,18],"capInsets":[0,0,0,0]}],[0],0,[0],[1],[4]]]]